sat_dependency_resolver/__init__.py
sat_dependency_resolver/ai_agent.py
sat_dependency_resolver/api.py
sat_dependency_resolver/encoder.py
sat_dependency_resolver/resolver.py
sat_dependency_resolver-0.1.7.dist-info/licenses/LICENSE
sat_dependency_resolver-0.1.7.dist-info/METADATA
sat_dependency_resolver-0.1.7.dist-info/WHEEL
sat_dependency_resolver-0.1.7.dist-info/top_level.txt
sat_dependency_resolver-0.1.7.dist-info/RECORD
