Metadata-Version: 2.4
Name: sat-dependency-resolver
Version: 0.1.7
Summary: Universal dependency resolver using SAT solvers
Home-page: https://github.com/Apollo87z/sat-dependency-resolver
Author:  Shehan Horadagoda
Author-email: shehan87h@gmail.com
Classifier: Development Status :: 4 - Beta
Classifier: Intended Audience :: Developers
Classifier: Topic :: Software Development :: Libraries
Classifier: License :: OSI Approved :: MIT License
Classifier: Programming Language :: Python :: 3
Classifier: Programming Language :: Python :: 3.8
Classifier: Programming Language :: Python :: 3.9
Classifier: Programming Language :: Python :: 3.10
Classifier: Programming Language :: Python :: 3.11
Requires-Python: >=3.8
License-File: LICENSE
Requires-Dist: python-sat>=0.1.7.dev18
Requires-Dist: requests>=2.27.0
Provides-Extra: api
Requires-Dist: flask>=2.0.0; extra == "api"
Provides-Extra: ai
Requires-Dist: anthropic>=0.18.0; extra == "ai"
Requires-Dist: python-dotenv>=1.0.0; extra == "ai"
Dynamic: author
Dynamic: author-email
Dynamic: classifier
Dynamic: description
Dynamic: description-content-type
Dynamic: home-page
Dynamic: license-file
Dynamic: provides-extra
Dynamic: requires-dist
Dynamic: requires-python
Dynamic: summary
